odoo/addons/report_xml/README.rst
odoo/addons/report_xml/__init__.py
odoo/addons/report_xml/__manifest__.py
odoo/addons/report_xml/hooks.py
odoo/addons/report_xml/controllers/__init__.py
odoo/addons/report_xml/controllers/main.py
odoo/addons/report_xml/demo/demo_report.xml
odoo/addons/report_xml/demo/demo_report.xsd
odoo/addons/report_xml/demo/report.xml
odoo/addons/report_xml/i18n/am.po
odoo/addons/report_xml/i18n/ar.po
odoo/addons/report_xml/i18n/bg.po
odoo/addons/report_xml/i18n/bs.po
odoo/addons/report_xml/i18n/ca.po
odoo/addons/report_xml/i18n/cs.po
odoo/addons/report_xml/i18n/da.po
odoo/addons/report_xml/i18n/de.po
odoo/addons/report_xml/i18n/el_GR.po
odoo/addons/report_xml/i18n/en.po
odoo/addons/report_xml/i18n/en_GB.po
odoo/addons/report_xml/i18n/es.po
odoo/addons/report_xml/i18n/es_AR.po
odoo/addons/report_xml/i18n/es_CL.po
odoo/addons/report_xml/i18n/es_CO.po
odoo/addons/report_xml/i18n/es_CR.po
odoo/addons/report_xml/i18n/es_DO.po
odoo/addons/report_xml/i18n/es_EC.po
odoo/addons/report_xml/i18n/es_ES.po
odoo/addons/report_xml/i18n/es_MX.po
odoo/addons/report_xml/i18n/es_PE.po
odoo/addons/report_xml/i18n/es_PY.po
odoo/addons/report_xml/i18n/es_VE.po
odoo/addons/report_xml/i18n/et.po
odoo/addons/report_xml/i18n/eu.po
odoo/addons/report_xml/i18n/fa.po
odoo/addons/report_xml/i18n/fi.po
odoo/addons/report_xml/i18n/fr.po
odoo/addons/report_xml/i18n/fr_CA.po
odoo/addons/report_xml/i18n/fr_CH.po
odoo/addons/report_xml/i18n/gl.po
odoo/addons/report_xml/i18n/gl_ES.po
odoo/addons/report_xml/i18n/he.po
odoo/addons/report_xml/i18n/hr.po
odoo/addons/report_xml/i18n/hr_HR.po
odoo/addons/report_xml/i18n/hu.po
odoo/addons/report_xml/i18n/id.po
odoo/addons/report_xml/i18n/it.po
odoo/addons/report_xml/i18n/ja.po
odoo/addons/report_xml/i18n/ko.po
odoo/addons/report_xml/i18n/lt.po
odoo/addons/report_xml/i18n/lt_LT.po
odoo/addons/report_xml/i18n/lv.po
odoo/addons/report_xml/i18n/mk.po
odoo/addons/report_xml/i18n/mn.po
odoo/addons/report_xml/i18n/nb.po
odoo14_addon_report_xml-14.0.1.0.3.dist-info/METADATA
odoo14_addon_report_xml-14.0.1.0.3.dist-info/WHEEL
odoo14_addon_report_xml-14.0.1.0.3.dist-info/top_level.txt
odoo14_addon_report_xml-14.0.1.0.3.dist-info/RECORD
